{
  "name":"石燕平",
  "sex":"男",
  "birthday":"1994-06-27",
  "workSince":"2016-02-01",
  "exp":["毕业","年工作","年"],
  "nickname":"小石不识月",
  "firstName":"Shi",
  "lastName":"yanping",
  "slogan":"努力成为卓越并且专业的攻城狮",
  "tips":"Ctrl+p可以印本简历，打印时显示真名",
  "education":"本科",
  "phone":13260298521,
  "location":"Beijing·China",
  "qq":{
    "number":"594388036"
  },
  "website":"https://shiyanping.github.io",
  "github":"https://github.com/Shiyanping",
  "email":"594388036@qq.com",
  "intro":{
    "content":[
      "2年半工作经验，在当前的公司带3个实习生。",
      "毕业因为热爱前端，所以在实习公司通过自己的努力和前辈的帮忙，成为一名合格的前端攻城狮。",
      "熟悉前端流行的框架，使用 vue 搭建过中型后台管理系统和手机端页面。",
      "喜欢折腾，但是工作上比较务实，平时喜欢看一些技术文章。",
      "有小程序开发经验，目前线上的小程序有“成语大神”和“超级默契“。",
      "目前的主要工作内容为混合开发"
    ],
    "technology":{
      "title":"用过的技术栈：",
      "content":[
        "jquery","vue","stylus","less","gulp","webpack","各种UI框架（ Bootstrap, element-ui ）","JSBridge（H5与客户端交互框架）"
      ]
    }
  },
  "experience":[
    {
      "time":"2016.08-目前",
      "title":"北京酷划在线",
      "intro":"前端开发",
      "description":"主要负责淘新闻产品线（用户端和管理后台）及小程序的开发，规范前端开发流程及代码规范，协同产品经理确定需求，配合后端和客户端定义及联调接口，推动产品发展。",
      "tips":[
        {
          "title":"主要业绩：",
          "content":[
            "淘新闻从创立一直到现在，前端主要是我负责，产品从 0 一直做到目前月收入 2500万，DAU 270万左右。",
            "完成商城用户端开发，实现前后端分离。",
            "合理使用 vue 重构之前 jquery 的项目。在工作之余对官网进行响应式重构。",
            "协同后端同学完成管理平台的建设（数据平台，管理后台，投放后台等）。",
            "完成各种 app 内嵌的 H5页面（活动页，分享落地页，app 内部说明页，任务大厅等功能页）",
            "推动完善H5和客户端的交互流程（scheme -> window 挂载方法 -> JSBridge）。",
            "配合客户端优化淘新闻 app 中的内容详情页加载速度，从之前打开一片新闻1.5s优化到400ms，由于后面JS广告出问题，将客户端缓存去掉，所以现在加载速度会有所变慢。"
          ]
        }
      ],
      "technology":[
        {
          "title":"技术栈：",
          "content":[
            "vue","less","scss","stylus","element-ui","gulp","webpack","jquery"
          ]
        }
      ]
    },
    {
      "time":"2016.01-2016.08",
      "title":"北京魔力爱普",
      "intro":"前端实习生-前端开发",
      "description":"在公司期间，大部分精力都用于前端学习及锻炼型的业务开发。很感谢我的 leader 可以让我根据项目逐步学习，代码从最初的 css,js 转到 less,jquery，从 less,jquery 转到 scss,stylus,vue。熟悉了 gulp，基于 gulp 做了部分前端自动化构建的工具。同时也更加深入的学习了 vue 框架，了解了 react,angular。",
      "tips":[
        {
          "title":"主要业绩：",
          "content":[
            "主要完成 app 内嵌H5页和微信公众号的开发。",
            "完善公司官网（添加动画）及PC端管理后台。",
            "负责和后台人员进行沟通，完成产品的迭代",
            "利用工作之余学习 vue 和前端工程化工具。"
          ]
        }
      ],
      "technology":[
        {
          "title":"技术栈：",
          "content":[
            "js","css","jquery","vue","bootstrap","gulp"
          ]
        }
      ]
    }
  ],
  "skill":[
    {
      "name":"JavaScript",
      "percent":"70%"
    },
    {
      "name":"Vue",
      "percent":"65%"
    },
    {
      "name":"Css",
      "percent":"80%"
    },
    {
      "name":"Bootstrap（栅格布局的概念）",
      "percent":"85%"
    },
    {
      "name":"Git 及 svn",
      "percent":"75%"
    },
    {
      "name":"PhotoShop",
      "percent":"60%"
    }
  ],
  "project":[
    {
      "time":"2017.04-2017.05",
      "title":"酷划商城",
      "intro":"用于消耗酷划不同产品的用户积分",
      "description":"同一时间段内完成了商城管理后台和用户端的页面开发，在之前公司没有任何项目实现前后端分离的情况下，用户端商城成功完成前后端分离",
      "tips":[
        {
          "title":"主要功能及总结：",
          "content":[
            "用户端商城同其他的商城一样，有完善的购买流程，初期同一套代码用在了三条产品线上",
            "完成了商城管理后台（商品管理，订单管理，物流管理）",
            "初期后端架构师的意思是商城只用于消耗用户积分，与业务逻辑区分，但是后续在持续的迭代中，商城加入了很多产品的业务逻辑，就导致代码管理不方便，在今年4月初，我将三个产品线代码进行了分离。",
            "目前正在同后端及项目经理协商，使用 vue 重构客户端和管理后台"
          ]
        }
      ],
      "technology":[
        {
          "title":"技术栈：",
          "content":[
            "jquery","artTemplate","less"
          ]
        }
      ]
    },
    {
      "time":"2017.12-2018.01",
      "title":"酷划官网",
      "intro":"https://www.coohua.com",
      "description":"自毕业后创建与维护一个个人网站。在学nodejs之前，是基于drupal做的。自己独立开发的主题，广受欢迎。在学习了nodejs后，后端基于nodejs的express和Mongodb，前端基于angularjs和bootstrap使用restful风格重做了一遍。历时1年。整个网站的迭代是我整个技术栈成长的缩影。",
      "tips":[
        {
          "title":"实现的主要功能：",
          "content":[
            "用户登录注册以及用户管理。",
            "创建管理有序且有层级关系的教程文档。",
            "针对注册用户订购网站会员的订单系统。",
            "博客系统。"
          ]
        }
      ],
      "technology":[
        {
          "title":"技术栈：",
          "content":[
            "css3","html","js"
          ]
        }
      ]
    },
    {
      "time":"2015.02-2015.10",
      "title":"听说通",
      "intro":"一个K12领域在线教育产品",
      "description":"在此期间参与了一个教育产品包括学生端、老师端、微信家长端以及学校管理员管理后台几个系统的前端方便的工作。微信家长端是基于vue.js制作，其他部分是基于angular和bootstrap利用gulp等一系列nodejs构建完成。",
      "tips":[
        {
          "title":"实现的主要功能：",
          "content":[
            "老师端：根据现有内容库发布、批改作业。管理班级和学生等。",
            "学生端：查看和完成老师布置作业。",
            "家长端：通过微信公众号绑定和管理自己的孩子方便查看孩子的作业情况。",
            "学校管理后台：管理老师学生教材等。"
          ]
        }
      ],
      "technology":[
        {
          "title":"技术栈：",
          "content":[
            "node.js","angular","scss","gulp","bootstrap"
          ]
        }
      ]
    },
    {
      "time":"2015.11-2016.08",
      "title":"U学",
      "intro":"一个闯关形式的在线教育产品",
      "description":"与之前的听说通类似。如果之前的产品是淘宝模式，那么这个产品就是京东模式。同样包括学生端，老师端和微信家长端以及管理后台。除此之外，我们还利用ionic基于前端技术制作老师移动端分别打包成了android和ios应用。",
      "technology":[
        {
          "title":"技术栈：",
          "content":[
            "node.js","angular","scss","gulp","bootstrap"
          ]
        }
      ]
    },
    {
      "time":"2014.03-2015.01",
      "title":"Trafish",
      "intro":"一个入境游在线旅游产品",
      "description":"这个产品是前后端混合开发的。都是写的jsp页面。完成了线上订购旅游产品的一个网站和管理订单和用户的管理后台。"
    },
    {
      "time":"2017.10-2017.10",
      "title":"黄龙客栈",
      "intro":"一个聚会娱乐小程序。",
      "description":"个人为主体的，业余做着玩的防止聚会无聊的小程序。在微信小程序中搜索'黄龙客栈'即可查看。"
    }
  ],
  "usually":[
    {
      "name":"GitHub",
      "link":"https://github.com/eternityspring",
      "description":"分享一些我的小作品 结交志同道合的朋友"
    },
    {
      "name":"知乎",
      "link":"https://www.zhihu.com/people/790313188",
      "description":"搜索解决一些疑问 探索新奇"
    },
    {
      "name":"MDN",
      "link":"https://developer.mozilla.org",
      "description":"查阅一些技术文档"
    },
    {
      "name":"Behance",
      "description":"寻找灵感探索新奇"
    },
    {
      "name":"Dribbble",
      "link":"https://dribbble.com/eternityspring",
      "description":"寻找灵感探索新奇"
    },
    {
      "name":"CodePen",
      "link":"http://codepen.io/eternityspring",
      "description":"探索和分享好的代码"
    }
  ]
}
